cronotrack/__init__.py
cronotrack/__main__.py
cronotrack/app.py
cronotrack/services/__init__.py
cronotrack/services/chrono_timer.py
cronotrack/services/ui_manger.py
cronotrack/services/ui_worker.py
cronotrack-0.1.1.dist-info/LICENSE
cronotrack-0.1.1.dist-info/METADATA
cronotrack-0.1.1.dist-info/WHEEL
cronotrack-0.1.1.dist-info/top_level.txt
cronotrack-0.1.1.dist-info/RECORD
