Metadata-Version: 2.1
Name: cronotrack
Version: 0.1.1
Summary: CLI App to track time
Home-page: https://github.com/salpreh/cronotrack
Author: salpreh
Author-email: salva.perez46@gmail.com
License: GPL-3.0
Platform: UNKNOWN
